DESCRIPTION
LICENSE
LICENSE-3RD-PARTY
MANIFEST.in
README.md
VERSION.txt
setup.py
tukio/__init__.py
tukio/broker.py
tukio/dag.py
tukio/engine.py
tukio/event.py
tukio/utils.py
tukio/workflow.py
tukio.egg-info/PKG-INFO
tukio.egg-info/SOURCES.txt
tukio.egg-info/dependency_links.txt
tukio.egg-info/top_level.txt
tukio/task/__init__.py
tukio/task/factory.py
tukio/task/holder.py
tukio/task/join.py
tukio/task/task.py
tukio/task/template.py